{"nodes": [{"id": "d_it_ppid_baznas_turbo_json", "label": "turbo.json", "file_type": "code", "source_file": "turbo.json", "source_location": "L1"}, {"id": "ppid_baznas_turbo_schema", "label": "$schema", "file_type": "code", "source_file": "turbo.json", "source_location": "L2"}, {"id": "ppid_baznas_turbo_globalenv", "label": "globalEnv", "file_type": "code", "source_file": "turbo.json", "source_location": "L3"}, {"id": "ppid_baznas_turbo_tasks", "label": "tasks", "file_type": "code", "source_file": "turbo.json", "source_location": "L4"}, {"id": "ppid_baznas_turbo_tasks_build", "label": "build", "file_type": "code", "source_file": "turbo.json", "source_location": "L5"}, {"id": "ppid_baznas_turbo_build_dependson", "label": "dependsOn", "file_type": "code", "source_file": "turbo.json", "source_location": "L6"}, {"id": "ppid_baznas_turbo_build_outputs", "label": "outputs", "file_type": "code", "source_file": "turbo.json", "source_location": "L7"}, {"id": "ppid_baznas_turbo_tasks_dev", "label": "dev", "file_type": "code", "source_file": "turbo.json", "source_location": "L9"}, {"id": "ppid_baznas_turbo_dev_cache", "label": "cache", "file_type": "code", "source_file": "turbo.json", "source_location": "L10"}, {"id": "ppid_baznas_turbo_dev_persistent", "label": "persistent", "file_type": "code", "source_file": "turbo.json", "source_location": "L11"}, {"id": "ppid_baznas_turbo_tasks_lint", "label": "lint", "file_type": "code", "source_file": "turbo.json", "source_location": "L13"}, {"id": "ppid_baznas_turbo_lint_dependson", "label": "dependsOn", "file_type": "code", "source_file": "turbo.json", "source_location": "L13"}, {"id": "ppid_baznas_turbo_tasks_test", "label": "test", "file_type": "code", "source_file": "turbo.json", "source_location": "L14"}, {"id": "ppid_baznas_turbo_test_dependson", "label": "dependsOn", "file_type": "code", "source_file": "turbo.json", "source_location": "L14"}, {"id": "ppid_baznas_turbo_tasks_db_generate", "label": "db:generate", "file_type": "code", "source_file": "turbo.json", "source_location": "L15"}, {"id": "ppid_baznas_turbo_db_generate_cache", "label": "cache", "file_type": "code", "source_file": "turbo.json", "source_location": "L15"}, {"id": "ppid_baznas_turbo_tasks_db_migrate", "label": "db:migrate", "file_type": "code", "source_file": "turbo.json", "source_location": "L16"}, {"id": "ppid_baznas_turbo_db_migrate_cache", "label": "cache", "file_type": "code", "source_file": "turbo.json", "source_location": "L16"}, {"id": "ppid_baznas_turbo_tasks_db_seed", "label": "db:seed", "file_type": "code", "source_file": "turbo.json", "source_location": "L17"}, {"id": "ppid_baznas_turbo_db_seed_cache", "label": "cache", "file_type": "code", "source_file": "turbo.json", "source_location": "L17"}], "edges": [{"source": "d_it_ppid_baznas_turbo_json", "target": "ppid_baznas_turbo_schema", "relation": "contains", "confidence": "EXTRACTED", "source_file": "turbo.json", "source_location": "L2", "weight": 1.0}, {"source": "d_it_ppid_baznas_turbo_json", "target": "ppid_baznas_turbo_globalenv", "relation": "contains", "confidence": "EXTRACTED", "source_file": "turbo.json", "source_location": "L3", "weight": 1.0}, {"source": "ppid_baznas_turbo_globalenv", "target": "ref_node_env", "relation": "extends", "confidence": "EXTRACTED", "source_file": "turbo.json", "source_location": "L3", "weight": 1.0, "context": "import"}, {"source": "ppid_baznas_turbo_globalenv", "target": "ref_database_url", "relation": "extends", "confidence": "EXTRACTED", "source_file": "turbo.json", "source_location": "L3", "weight": 1.0, "context": "import"}, {"source": "ppid_baznas_turbo_globalenv", "target": "ref_nextauth_secret", "relation": "extends", "confidence": "EXTRACTED", "source_file": "turbo.json", "source_location": "L3", "weight": 1.0, "context": "import"}, {"source": "d_it_ppid_baznas_turbo_json", "target": "ppid_baznas_turbo_tasks", "relation": "contains", "confidence": "EXTRACTED", "source_file": "turbo.json", "source_location": "L4", "weight": 1.0}, {"source": "ppid_baznas_turbo_tasks", "target": "ppid_baznas_turbo_tasks_build", "relation": "contains", "confidence": "EXTRACTED", "source_file": "turbo.json", "source_location": "L5", "weight": 1.0}, {"source": "ppid_baznas_turbo_tasks_build", "target": "ppid_baznas_turbo_build_dependson", "relation": "contains", "confidence": "EXTRACTED", "source_file": "turbo.json", "source_location": "L6", "weight": 1.0}, {"source": "ppid_baznas_turbo_build_dependson", "target": "ref_build", "relation": "extends", "confidence": "EXTRACTED", "source_file": "turbo.json", "source_location": "L6", "weight": 1.0, "context": "import"}, {"source": "ppid_baznas_turbo_tasks_build", "target": "ppid_baznas_turbo_build_outputs", "relation": "contains", "confidence": "EXTRACTED", "source_file": "turbo.json", "source_location": "L7", "weight": 1.0}, {"source": "ppid_baznas_turbo_build_outputs", "target": "ref_next", "relation": "extends", "confidence": "EXTRACTED", "source_file": "turbo.json", "source_location": "L7", "weight": 1.0, "context": "import"}, {"source": "ppid_baznas_turbo_build_outputs", "target": "ref_next_cache", "relation": "extends", "confidence": "EXTRACTED", "source_file": "turbo.json", "source_location": "L7", "weight": 1.0, "context": "import"}, {"source": "ppid_baznas_turbo_build_outputs", "target": "ref_dist", "relation": "extends", "confidence": "EXTRACTED", "source_file": "turbo.json", "source_location": "L7", "weight": 1.0, "context": "import"}, {"source": "ppid_baznas_turbo_tasks", "target": "ppid_baznas_turbo_tasks_dev", "relation": "contains", "confidence": "EXTRACTED", "source_file": "turbo.json", "source_location": "L9", "weight": 1.0}, {"source": "ppid_baznas_turbo_tasks_dev", "target": "ppid_baznas_turbo_dev_cache", "relation": "contains", "confidence": "EXTRACTED", "source_file": "turbo.json", "source_location": "L10", "weight": 1.0}, {"source": "ppid_baznas_turbo_tasks_dev", "target": "ppid_baznas_turbo_dev_persistent", "relation": "contains", "confidence": "EXTRACTED", "source_file": "turbo.json", "source_location": "L11", "weight": 1.0}, {"source": "ppid_baznas_turbo_tasks", "target": "ppid_baznas_turbo_tasks_lint", "relation": "contains", "confidence": "EXTRACTED", "source_file": "turbo.json", "source_location": "L13", "weight": 1.0}, {"source": "ppid_baznas_turbo_tasks_lint", "target": "ppid_baznas_turbo_lint_dependson", "relation": "contains", "confidence": "EXTRACTED", "source_file": "turbo.json", "source_location": "L13", "weight": 1.0}, {"source": "ppid_baznas_turbo_lint_dependson", "target": "ref_lint", "relation": "extends", "confidence": "EXTRACTED", "source_file": "turbo.json", "source_location": "L13", "weight": 1.0, "context": "import"}, {"source": "ppid_baznas_turbo_tasks", "target": "ppid_baznas_turbo_tasks_test", "relation": "contains", "confidence": "EXTRACTED", "source_file": "turbo.json", "source_location": "L14", "weight": 1.0}, {"source": "ppid_baznas_turbo_tasks_test", "target": "ppid_baznas_turbo_test_dependson", "relation": "contains", "confidence": "EXTRACTED", "source_file": "turbo.json", "source_location": "L14", "weight": 1.0}, {"source": "ppid_baznas_turbo_test_dependson", "target": "ref_build", "relation": "extends", "confidence": "EXTRACTED", "source_file": "turbo.json", "source_location": "L14", "weight": 1.0, "context": "import"}, {"source": "ppid_baznas_turbo_tasks", "target": "ppid_baznas_turbo_tasks_db_generate", "relation": "contains", "confidence": "EXTRACTED", "source_file": "turbo.json", "source_location": "L15", "weight": 1.0}, {"source": "ppid_baznas_turbo_tasks_db_generate", "target": "ppid_baznas_turbo_db_generate_cache", "relation": "contains", "confidence": "EXTRACTED", "source_file": "turbo.json", "source_location": "L15", "weight": 1.0}, {"source": "ppid_baznas_turbo_tasks", "target": "ppid_baznas_turbo_tasks_db_migrate", "relation": "contains", "confidence": "EXTRACTED", "source_file": "turbo.json", "source_location": "L16", "weight": 1.0}, {"source": "ppid_baznas_turbo_tasks_db_migrate", "target": "ppid_baznas_turbo_db_migrate_cache", "relation": "contains", "confidence": "EXTRACTED", "source_file": "turbo.json", "source_location": "L16", "weight": 1.0}, {"source": "ppid_baznas_turbo_tasks", "target": "ppid_baznas_turbo_tasks_db_seed", "relation": "contains", "confidence": "EXTRACTED", "source_file": "turbo.json", "source_location": "L17", "weight": 1.0}, {"source": "ppid_baznas_turbo_tasks_db_seed", "target": "ppid_baznas_turbo_db_seed_cache", "relation": "contains", "confidence": "EXTRACTED", "source_file": "turbo.json", "source_location": "L17", "weight": 1.0}]}